drawdata/__init__.py
drawdata/static/bar_widget.css
drawdata/static/bar_widget.js
drawdata/static/scatter_widget.css
drawdata/static/scatter_widget.js
drawdata-0.3.9.dist-info/licenses/LICENSE
drawdata-0.3.9.dist-info/METADATA
drawdata-0.3.9.dist-info/WHEEL
drawdata-0.3.9.dist-info/top_level.txt
drawdata-0.3.9.dist-info/RECORD
