Metadata-Version: 2.4
Name: drawdata
Version: 0.3.9
Summary: draw a dataset from inside Jupyter
Author: Vincent D. Warmerdam
License: MIT
Classifier: Intended Audience :: Developers
Classifier: Intended Audience :: Science/Research
Classifier: Programming Language :: Python :: 3
Classifier: Programming Language :: Python :: 3.10
Classifier: Programming Language :: Python :: 3.11
Classifier: Programming Language :: Python :: 3.12
Classifier: License :: OSI Approved :: MIT License
Classifier: Topic :: Scientific/Engineering
Requires-Python: >=3.10
License-File: LICENSE
Requires-Dist: anywidget>=0.9.2
Dynamic: license-file
